{"5f1c59c9fa523c3aa793bf3c":{"_id":"5f1c59c9fa523c3aa793bf3c","name":"Danika Danika","trips":2500000,"airline":[{"id":5,"name":"Eva Air","country":"Taiwan","logo":"https://upload.wikimedia.org/wikipedia/en/thumb/e/ed/EVA_Air_logo.svg/250px-EVA_Air_logo.svg.png","slogan":"Sharing the World, Flying Together","head_quaters":"376, Hsin-Nan Rd., Sec. 1, Luzhu, Taoyuan City, Taiwan","website":"www.evaair.com","established":"1989"}],"__v":0},"5f1c59cbfa523c3aa793c03a":{"_id":"5f1c59cbfa523c3aa793c03a","name":"Mathilda Capone","trips":835,"airline":{"id":1,"name":"Quatar Airways","country":"Quatar","logo":"https://upload.wikimedia.org/wikipedia/en/thumb/9/9b/Qatar_Airways_Logo.svg/300px-Qatar_Airways_Logo.svg.png","slogan":"Going Places Together","head_quaters":"Qatar Airways Towers, Doha, Qatar","website":"www.qatarairways.com","established":"1994"},"__v":0},"5f1c59c9fa523c3aa793bf41":{"_id":"5f1c59c9fa523c3aa793bf41","name":"Brett Jo-Ank","trips":824,"airline":{"id":7,"name":"Deutsche Lufthansa AG","country":"Germany","logo":"https://upload.wikimedia.org/wikipedia/commons/thumb/b/b8/Lufthansa_Logo_2018.svg/300px-Lufthansa_Logo_2018.svg.png","slogan":"Say yes to the world","head_quaters":"Cologne, Germany","website":"lufthansa.com","established":"1953"},"__v":0},"5f1c59c9fa523c3aa793bf46":{"_id":"5f1c59c9fa523c3aa793bf46","name":"Lyda Gladys","trips":287,"airline":[{"id":4,"name":"Emirates","country":"Dubai","logo":"https://upload.wikimedia.org/wikipedia/commons/thumb/d/d0/Emirates_logo.svg/150px-Emirates_logo.svg.png","slogan":"From Dubai to destinations around the world.","head_quaters":"Garhoud, Dubai, United Arab Emirates","website":"www.emirates.com/","established":"1985"}],"__v":0},"5f1c59c9fa523c3aa793bf4b":{"_id":"5f1c59c9fa523c3aa793bf4b","name":"De Jemena","trips":275,"airline":{"id":1,"name":"Quatar Airways","country":"Quatar","logo":"https://upload.wikimedia.org/wikipedia/en/thumb/9/9b/Qatar_Airways_Logo.svg/300px-Qatar_Airways_Logo.svg.png","slogan":"Going Places Together","head_quaters":"Qatar Airways Towers, Doha, Qatar","website":"www.qatarairways.com","established":"1994"},"__v":0},"c7e9286b-f192-4ca7-a1c7-763d6a1a8e80":{"name":"wri","trips":250,"country":"Taiwan","airline":[{"id":3,"name":"Eva Air","country":"Taiwan","logo":"https://upload.wikimedia.org/wikipedia/en/thumb/e/ed/EVA_Air_logo.svg/250px-EVA_Air_logo.svg.png","slogan":"Sharing the World, Flying Together","head_quaters":"376, Hsin-Nan Rd., Sec. 1, Luzhu, Taoyuan City, Taiwan","website":"www.evaair.com","established":"1989"},{"id":4,"name":"Eva Air","country":"Taiwan","logo":"https://upload.wikimedia.org/wikipedia/en/thumb/e/ed/EVA_Air_logo.svg/250px-EVA_Air_logo.svg.png","slogan":"Sharing the World, Flying Together","head_quaters":"376, Hsin-Nan Rd., Sec. 1, Luzhu, Taoyuan City, Taiwan","website":"www.evaair.com","established":"1989"}],"__v":0,"_id":"c7e9286b-f192-4ca7-a1c7-763d6a1a8e80"},"97b8139b-beb6-469c-b5e7-09ea1cc914b3":{"name":"wri","trips":250,"country":"Taiwan","airline":[{"id":3,"name":"Eva Air","country":"Taiwan","logo":"https://upload.wikimedia.org/wikipedia/en/thumb/e/ed/EVA_Air_logo.svg/250px-EVA_Air_logo.svg.png","slogan":"Sharing the World, Flying Together","head_quaters":"376, Hsin-Nan Rd., Sec. 1, Luzhu, Taoyuan City, Taiwan","website":"www.evaair.com","established":"1989"},{"id":4,"name":"Eva Air","country":"Taiwan","logo":"https://upload.wikimedia.org/wikipedia/en/thumb/e/ed/EVA_Air_logo.svg/250px-EVA_Air_logo.svg.png","slogan":"Sharing the World, Flying Together","head_quaters":"376, Hsin-Nan Rd., Sec. 1, Luzhu, Taoyuan City, Taiwan","website":"www.evaair.com","established":"1989"}],"__v":0,"_id":"97b8139b-beb6-469c-b5e7-09ea1cc914b3"},"00c5d4a9-4ffa-4c1e-b2e3-ebf182bcb366":{"name":"wri","trips":250,"country":"Taiwan","airline":[{"id":3,"name":"Eva Air","country":"Taiwan","logo":"https://upload.wikimedia.org/wikipedia/en/thumb/e/ed/EVA_Air_logo.svg/250px-EVA_Air_logo.svg.png","slogan":"Sharing the World, Flying Together","head_quaters":"376, Hsin-Nan Rd., Sec. 1, Luzhu, Taoyuan City, Taiwan","website":"www.evaair.com","established":"1989"},{"id":4,"name":"Eva Air","country":"Taiwan","logo":"https://upload.wikimedia.org/wikipedia/en/thumb/e/ed/EVA_Air_logo.svg/250px-EVA_Air_logo.svg.png","slogan":"Sharing the World, Flying Together","head_quaters":"376, Hsin-Nan Rd., Sec. 1, Luzhu, Taoyuan City, Taiwan","website":"www.evaair.com","established":"1989"}],"__v":0,"_id":"00c5d4a9-4ffa-4c1e-b2e3-ebf182bcb366"},"7172b404-a888-4884-9de7-bde2b7acbf36":{"name":"kjsg","trips":250,"airline":[{"id":5,"name":"Eva Air","country":"Taiwan","logo":"https://upload.wikimedia.org/wikipedia/en/thumb/e/ed/EVA_Air_logo.svg/250px-EVA_Air_logo.svg.png","slogan":"Sharing the World, Flying Together","head_quaters":"376, Hsin-Nan Rd., Sec. 1, Luzhu, Taoyuan City, Taiwan","website":"www.evaair.com","established":"1989"}],"__v":0,"_id":"7172b404-a888-4884-9de7-bde2b7acbf36"},"a65a3a9a-68bd-4933-b90a-412f489f06fd":{"name":"kjsg","trips":250,"airline":[{"id":5,"name":"Eva Air","country":"Taiwan","logo":"https://upload.wikimedia.org/wikipedia/en/thumb/e/ed/EVA_Air_logo.svg/250px-EVA_Air_logo.svg.png","slogan":"Sharing the World, Flying Together","head_quaters":"376, Hsin-Nan Rd., Sec. 1, Luzhu, Taoyuan City, Taiwan","website":"www.evaair.com","established":"1989"}],"__v":0,"_id":"a65a3a9a-68bd-4933-b90a-412f489f06fd"},"a9f446e0-c17b-4b21-ab47-18ef403688e3":{"name":"kjsg","trips":250,"airline":[{"id":5,"name":"Eva Air","country":"Taiwan","logo":"https://upload.wikimedia.org/wikipedia/en/thumb/e/ed/EVA_Air_logo.svg/250px-EVA_Air_logo.svg.png","slogan":"Sharing the World, Flying Together","head_quaters":"376, Hsin-Nan Rd., Sec. 1, Luzhu, Taoyuan City, Taiwan","website":"www.evaair.com","established":"1989"}],"__v":0,"_id":"a9f446e0-c17b-4b21-ab47-18ef403688e3"},"df411ac3-1d61-44af-9c49-747a6493870f":{"name":"kjsg","trips":250,"airline":[{"id":5,"name":"Eva Air","country":"Taiwan","logo":"https://upload.wikimedia.org/wikipedia/en/thumb/e/ed/EVA_Air_logo.svg/250px-EVA_Air_logo.svg.png","slogan":"Sharing the World, Flying Together","head_quaters":"376, Hsin-Nan Rd., Sec. 1, Luzhu, Taoyuan City, Taiwan","website":"www.evaair.com","established":"1989"}],"__v":0,"_id":"df411ac3-1d61-44af-9c49-747a6493870f"},"bc5eaf01-a460-4c33-a669-0313409d527e":{"name":"kjsg","trips":250,"airline":[{"id":5,"name":"Eva Air","country":"Taiwan","logo":"https://upload.wikimedia.org/wikipedia/en/thumb/e/ed/EVA_Air_logo.svg/250px-EVA_Air_logo.svg.png","slogan":"Sharing the World, Flying Together","head_quaters":"376, Hsin-Nan Rd., Sec. 1, Luzhu, Taoyuan City, Taiwan","website":"www.evaair.com","established":"1989"}],"__v":0,"_id":"bc5eaf01-a460-4c33-a669-0313409d527e"},"27756634-9003-4ce3-a02a-0d834582443b":{"name":"kjsg","trips":1,"airline":[{"id":5,"name":"Eva Air","country":"Taiwan","logo":"https://upload.wikimedia.org/wikipedia/en/thumb/e/ed/EVA_Air_logo.svg/250px-EVA_Air_logo.svg.png","slogan":"Sharing the World, Flying Together","head_quaters":"376, Hsin-Nan Rd., Sec. 1, Luzhu, Taoyuan City, Taiwan","website":"www.evaair.com","established":"1989"}],"__v":0,"_id":"27756634-9003-4ce3-a02a-0d834582443b"},"2155470c-5798-41ad-9bab-f6daaa21338c":{"name":"kjsg","trips":250,"airline":[{"id":5,"name":"Eva Air","country":"Taiwan","logo":"https://upload.wikimedia.org/wikipedia/en/thumb/e/ed/EVA_Air_logo.svg/250px-EVA_Air_logo.svg.png","slogan":"Sharing the World, Flying Together","head_quaters":"376, Hsin-Nan Rd., Sec. 1, Luzhu, Taoyuan City, Taiwan","website":"www.evaair.com","established":"1989"}],"__v":0,"_id":"2155470c-5798-41ad-9bab-f6daaa21338c"},"8e257fce-3c3f-4a1b-8881-7d78d9baa0a7":{"name":"kjsg","trips":1,"airline":[{"id":5,"name":"Eva Air","country":"Taiwan","logo":"https://upload.wikimedia.org/wikipedia/en/thumb/e/ed/EVA_Air_logo.svg/250px-EVA_Air_logo.svg.png","slogan":"Sharing the World, Flying Together","head_quaters":"376, Hsin-Nan Rd., Sec. 1, Luzhu, Taoyuan City, Taiwan","website":"www.evaair.com","established":"1989"}],"__v":0,"_id":"8e257fce-3c3f-4a1b-8881-7d78d9baa0a7"},"9e745a79-18a2-47c1-a7b5-bbbcda9a8395":{"name":"bane","trips":1,"airline":[{"id":5,"name":"Eva Air","country":"Taiwan","logo":"https://upload.wikimedia.org/wikipedia/en/thumb/e/ed/EVA_Air_logo.svg/250px-EVA_Air_logo.svg.png","slogan":"Sharing the World, Flying Together","head_quaters":"376, Hsin-Nan Rd., Sec. 1, Luzhu, Taoyuan City, Taiwan","website":"www.evaair.com","established":"1989"}],"__v":0,"_id":"9e745a79-18a2-47c1-a7b5-bbbcda9a8395"},"1c10540c-f00d-402f-ac54-b812af5e26d4":{"name":"kjsg","trips":250,"airline":[{"id":5,"name":"Eva Air","country":"Taiwan","logo":"https://upload.wikimedia.org/wikipedia/en/thumb/e/ed/EVA_Air_logo.svg/250px-EVA_Air_logo.svg.png","slogan":"Sharing the World, Flying Together","head_quaters":"376, Hsin-Nan Rd., Sec. 1, Luzhu, Taoyuan City, Taiwan","website":"www.evaair.com","established":"1989"}],"__v":0,"_id":"1c10540c-f00d-402f-ac54-b812af5e26d4"},"7c96ff88-db27-4182-a64b-d03dcd026140":{"name":"kjsg","trips":250,"airline":[{"id":5,"name":"Eva Air","country":"Taiwan","logo":"https://upload.wikimedia.org/wikipedia/en/thumb/e/ed/EVA_Air_logo.svg/250px-EVA_Air_logo.svg.png","slogan":"Sharing the World, Flying Together","head_quaters":"376, Hsin-Nan Rd., Sec. 1, Luzhu, Taoyuan City, Taiwan","website":"www.evaair.com","established":"1989"}],"__v":0,"_id":"7c96ff88-db27-4182-a64b-d03dcd026140"},"bce7397b-0dc8-4c28-8920-0f75c6132aa8":{"name":"kjsg","trips":250,"airline":[{"id":5,"name":"Eva Air","country":"Taiwan","logo":"https://upload.wikimedia.org/wikipedia/en/thumb/e/ed/EVA_Air_logo.svg/250px-EVA_Air_logo.svg.png","slogan":"Sharing the World, Flying Together","head_quaters":"376, Hsin-Nan Rd., Sec. 1, Luzhu, Taoyuan City, Taiwan","website":"www.evaair.com","established":"1989"}],"__v":0,"_id":"bce7397b-0dc8-4c28-8920-0f75c6132aa8"},"e20133b2-76fb-4809-9475-ea2f96da0d48":{"name":"kjsg","trips":250,"airline":[{"id":5,"name":"Eva Air","country":"Taiwan","logo":"https://upload.wikimedia.org/wikipedia/en/thumb/e/ed/EVA_Air_logo.svg/250px-EVA_Air_logo.svg.png","slogan":"Sharing the World, Flying Together","head_quaters":"376, Hsin-Nan Rd., Sec. 1, Luzhu, Taoyuan City, Taiwan","website":"www.evaair.com","established":"1989"}],"__v":0,"_id":"e20133b2-76fb-4809-9475-ea2f96da0d48"},"a6931f82-6a29-44df-98c0-10ae41df3ddb":{"name":"kjsg","trips":250,"airline":[{"id":5,"name":"Eva Air","country":"Taiwan","logo":"https://upload.wikimedia.org/wikipedia/en/thumb/e/ed/EVA_Air_logo.svg/250px-EVA_Air_logo.svg.png","slogan":"Sharing the World, Flying Together","head_quaters":"376, Hsin-Nan Rd., Sec. 1, Luzhu, Taoyuan City, Taiwan","website":"www.evaair.com","established":"1989"}],"__v":0,"_id":"a6931f82-6a29-44df-98c0-10ae41df3ddb"},"04f474af-644e-44eb-b07d-a0c0660ff91b":{"name":"kjsg","trips":1,"airline":[{"id":5,"name":"Eva Air","country":"Taiwan","logo":"https://upload.wikimedia.org/wikipedia/en/thumb/e/ed/EVA_Air_logo.svg/250px-EVA_Air_logo.svg.png","slogan":"Sharing the World, Flying Together","head_quaters":"376, Hsin-Nan Rd., Sec. 1, Luzhu, Taoyuan City, Taiwan","website":"www.evaair.com","established":"1989"}],"__v":0,"_id":"04f474af-644e-44eb-b07d-a0c0660ff91b"},"bc6e5b34-34c4-4ce4-be12-4d2706e38278":{"name":"kjsg","trips":250,"airline":[{"id":5,"name":"Eva Air","country":"Taiwan","logo":"https://upload.wikimedia.org/wikipedia/en/thumb/e/ed/EVA_Air_logo.svg/250px-EVA_Air_logo.svg.png","slogan":"Sharing the World, Flying Together","head_quaters":"376, Hsin-Nan Rd., Sec. 1, Luzhu, Taoyuan City, Taiwan","website":"www.evaair.com","established":"1989"}],"__v":0,"_id":"bc6e5b34-34c4-4ce4-be12-4d2706e38278"},"4ee7be79-7e6e-4235-a880-4258904aaea8":{"name":"kjsg","trips":1,"airline":[{"id":5,"name":"Eva Air","country":"Taiwan","logo":"https://upload.wikimedia.org/wikipedia/en/thumb/e/ed/EVA_Air_logo.svg/250px-EVA_Air_logo.svg.png","slogan":"Sharing the World, Flying Together","head_quaters":"376, Hsin-Nan Rd., Sec. 1, Luzhu, Taoyuan City, Taiwan","website":"www.evaair.com","established":"1989"}],"__v":0,"_id":"4ee7be79-7e6e-4235-a880-4258904aaea8"},"9f6747c2-aa8a-40d2-818e-4e7f015bed2f":{"name":"bane","trips":1,"airline":[{"id":5,"name":"Eva Air","country":"Taiwan","logo":"https://upload.wikimedia.org/wikipedia/en/thumb/e/ed/EVA_Air_logo.svg/250px-EVA_Air_logo.svg.png","slogan":"Sharing the World, Flying Together","head_quaters":"376, Hsin-Nan Rd., Sec. 1, Luzhu, Taoyuan City, Taiwan","website":"www.evaair.com","established":"1989"}],"__v":0,"_id":"9f6747c2-aa8a-40d2-818e-4e7f015bed2f"},"d92bc0ae-cf98-48ea-bc39-46dd130c1c12":{"name":"kjsg","trips":250,"airline":[{"id":5,"name":"Eva Air","country":"Taiwan","logo":"https://upload.wikimedia.org/wikipedia/en/thumb/e/ed/EVA_Air_logo.svg/250px-EVA_Air_logo.svg.png","slogan":"Sharing the World, Flying Together","head_quaters":"376, Hsin-Nan Rd., Sec. 1, Luzhu, Taoyuan City, Taiwan","website":"www.evaair.com","established":"1989"}],"__v":0,"_id":"d92bc0ae-cf98-48ea-bc39-46dd130c1c12"},"42b6b031-17e1-4f02-89c4-309622d8e9ac":{"name":"kjsg","trips":250,"airline":[{"id":5,"name":"Eva Air","country":"Taiwan","logo":"https://upload.wikimedia.org/wikipedia/en/thumb/e/ed/EVA_Air_logo.svg/250px-EVA_Air_logo.svg.png","slogan":"Sharing the World, Flying Together","head_quaters":"376, Hsin-Nan Rd., Sec. 1, Luzhu, Taoyuan City, Taiwan","website":"www.evaair.com","established":"1989"}],"__v":0,"_id":"42b6b031-17e1-4f02-89c4-309622d8e9ac"},"bbfa3c04-61d9-4cdc-98ba-25f7791c2668":{"name":"kjsg","trips":250,"airline":[{"id":5,"name":"Eva Air","country":"Taiwan","logo":"https://upload.wikimedia.org/wikipedia/en/thumb/e/ed/EVA_Air_logo.svg/250px-EVA_Air_logo.svg.png","slogan":"Sharing the World, Flying Together","head_quaters":"376, Hsin-Nan Rd., Sec. 1, Luzhu, Taoyuan City, Taiwan","website":"www.evaair.com","established":"1989"}],"__v":0,"_id":"bbfa3c04-61d9-4cdc-98ba-25f7791c2668"},"c8ae1312-43b8-4a70-acec-9b60fe741250":{"name":"kjsg","trips":250,"airline":[{"id":5,"name":"Eva Air","country":"Taiwan","logo":"https://upload.wikimedia.org/wikipedia/en/thumb/e/ed/EVA_Air_logo.svg/250px-EVA_Air_logo.svg.png","slogan":"Sharing the World, Flying Together","head_quaters":"376, Hsin-Nan Rd., Sec. 1, Luzhu, Taoyuan City, Taiwan","website":"www.evaair.com","established":"1989"}],"__v":0,"_id":"c8ae1312-43b8-4a70-acec-9b60fe741250"},"faebf29b-83d8-4400-830a-e3c6807abb14":{"name":"kjsg","trips":250,"airline":[{"id":5,"name":"Eva Air","country":"Taiwan","logo":"https://upload.wikimedia.org/wikipedia/en/thumb/e/ed/EVA_Air_logo.svg/250px-EVA_Air_logo.svg.png","slogan":"Sharing the World, Flying Together","head_quaters":"376, Hsin-Nan Rd., Sec. 1, Luzhu, Taoyuan City, Taiwan","website":"www.evaair.com","established":"1989"}],"__v":0,"_id":"faebf29b-83d8-4400-830a-e3c6807abb14"},"4832ce3c-3ae5-442a-a7a3-f4b13fe64bf1":{"name":"kjsg","trips":1,"airline":[{"id":5,"name":"Eva Air","country":"Taiwan","logo":"https://upload.wikimedia.org/wikipedia/en/thumb/e/ed/EVA_Air_logo.svg/250px-EVA_Air_logo.svg.png","slogan":"Sharing the World, Flying Together","head_quaters":"376, Hsin-Nan Rd., Sec. 1, Luzhu, Taoyuan City, Taiwan","website":"www.evaair.com","established":"1989"}],"__v":0,"_id":"4832ce3c-3ae5-442a-a7a3-f4b13fe64bf1"},"bdca08ca-4e46-4be5-8025-60d64d885cc2":{"name":"kjsg","trips":250,"airline":[{"id":5,"name":"Eva Air","country":"Taiwan","logo":"https://upload.wikimedia.org/wikipedia/en/thumb/e/ed/EVA_Air_logo.svg/250px-EVA_Air_logo.svg.png","slogan":"Sharing the World, Flying Together","head_quaters":"376, Hsin-Nan Rd., Sec. 1, Luzhu, Taoyuan City, Taiwan","website":"www.evaair.com","established":"1989"}],"__v":0,"_id":"bdca08ca-4e46-4be5-8025-60d64d885cc2"},"9fc55930-054a-441e-87cf-c203352cf359":{"name":"kjsg","trips":1,"airline":[{"id":5,"name":"Eva Air","country":"Taiwan","logo":"https://upload.wikimedia.org/wikipedia/en/thumb/e/ed/EVA_Air_logo.svg/250px-EVA_Air_logo.svg.png","slogan":"Sharing the World, Flying Together","head_quaters":"376, Hsin-Nan Rd., Sec. 1, Luzhu, Taoyuan City, Taiwan","website":"www.evaair.com","established":"1989"}],"__v":0,"_id":"9fc55930-054a-441e-87cf-c203352cf359"},"40b5cf8f-a836-4836-95dc-b270ffb11d0a":{"name":"bane","trips":1,"airline":[{"id":5,"name":"Eva Air","country":"Taiwan","logo":"https://upload.wikimedia.org/wikipedia/en/thumb/e/ed/EVA_Air_logo.svg/250px-EVA_Air_logo.svg.png","slogan":"Sharing the World, Flying Together","head_quaters":"376, Hsin-Nan Rd., Sec. 1, Luzhu, Taoyuan City, Taiwan","website":"www.evaair.com","established":"1989"}],"__v":0,"_id":"40b5cf8f-a836-4836-95dc-b270ffb11d0a"},"27bf061c-c0b0-4509-bcfa-aa82659f1433":{"name":"kjsg","trips":250,"airline":[{"id":5,"name":"Eva Air","country":"Taiwan","logo":"https://upload.wikimedia.org/wikipedia/en/thumb/e/ed/EVA_Air_logo.svg/250px-EVA_Air_logo.svg.png","slogan":"Sharing the World, Flying Together","head_quaters":"376, Hsin-Nan Rd., Sec. 1, Luzhu, Taoyuan City, Taiwan","website":"www.evaair.com","established":"1989"}],"__v":0,"_id":"27bf061c-c0b0-4509-bcfa-aa82659f1433"},"3c6fa8eb-7705-4c93-bbfc-25c581c68253":{"name":"kjsg","trips":250,"airline":[{"id":5,"name":"Eva Air","country":"Taiwan","logo":"https://upload.wikimedia.org/wikipedia/en/thumb/e/ed/EVA_Air_logo.svg/250px-EVA_Air_logo.svg.png","slogan":"Sharing the World, Flying Together","head_quaters":"376, Hsin-Nan Rd., Sec. 1, Luzhu, Taoyuan City, Taiwan","website":"www.evaair.com","established":"1989"}],"__v":0,"_id":"3c6fa8eb-7705-4c93-bbfc-25c581c68253"},"014d15cc-bd05-4827-9975-c8df802947b9":{"name":"kjsg","trips":250,"airline":[{"id":5,"name":"Eva Air","country":"Taiwan","logo":"https://upload.wikimedia.org/wikipedia/en/thumb/e/ed/EVA_Air_logo.svg/250px-EVA_Air_logo.svg.png","slogan":"Sharing the World, Flying Together","head_quaters":"376, Hsin-Nan Rd., Sec. 1, Luzhu, Taoyuan City, Taiwan","website":"www.evaair.com","established":"1989"}],"__v":0,"_id":"014d15cc-bd05-4827-9975-c8df802947b9"},"5e8ff4f6-4ec5-496b-9a52-85c65ebbb5fc":{"_id":"5e8ff4f6-4ec5-496b-9a52-85c65ebbb5fc","name":"kjsg","trips":250,"airline":[{"id":5,"name":"Eva Air","country":"Taiwan","logo":"https://upload.wikimedia.org/wikipedia/en/thumb/e/ed/EVA_Air_logo.svg/250px-EVA_Air_logo.svg.png","slogan":"Sharing the World, Flying Together","head_quaters":"376, Hsin-Nan Rd., Sec. 1, Luzhu, Taoyuan City, Taiwan","website":"www.evaair.com","established":"1989"}],"__v":0},"1bf579af-1bdf-41a3-bef6-3425cc2f8141":{"name":"kjsg","trips":250,"airline":[{"id":5,"name":"Eva Air","country":"Taiwan","logo":"https://upload.wikimedia.org/wikipedia/en/thumb/e/ed/EVA_Air_logo.svg/250px-EVA_Air_logo.svg.png","slogan":"Sharing the World, Flying Together","head_quaters":"376, Hsin-Nan Rd., Sec. 1, Luzhu, Taoyuan City, Taiwan","website":"www.evaair.com","established":"1989"}],"__v":0,"_id":"1bf579af-1bdf-41a3-bef6-3425cc2f8141"},"28b34a89-68f7-4306-b09b-9459a60bc104":{"name":"kjsg","trips":1,"airline":[{"id":5,"name":"Eva Air","country":"Taiwan","logo":"https://upload.wikimedia.org/wikipedia/en/thumb/e/ed/EVA_Air_logo.svg/250px-EVA_Air_logo.svg.png","slogan":"Sharing the World, Flying Together","head_quaters":"376, Hsin-Nan Rd., Sec. 1, Luzhu, Taoyuan City, Taiwan","website":"www.evaair.com","established":"1989"}],"__v":0,"_id":"28b34a89-68f7-4306-b09b-9459a60bc104"},"d947eac6-578c-48e6-acb1-ef1d2b5b61e0":{"name":"kjsg","trips":250,"airline":[{"id":5,"name":"Eva Air","country":"Taiwan","logo":"https://upload.wikimedia.org/wikipedia/en/thumb/e/ed/EVA_Air_logo.svg/250px-EVA_Air_logo.svg.png","slogan":"Sharing the World, Flying Together","head_quaters":"376, Hsin-Nan Rd., Sec. 1, Luzhu, Taoyuan City, Taiwan","website":"www.evaair.com","established":"1989"}],"__v":0,"_id":"d947eac6-578c-48e6-acb1-ef1d2b5b61e0"},"98f73556-06fb-4129-ba01-226f2d614fc6":{"name":"kjsg","trips":1,"airline":[{"id":5,"name":"Eva Air","country":"Taiwan","logo":"https://upload.wikimedia.org/wikipedia/en/thumb/e/ed/EVA_Air_logo.svg/250px-EVA_Air_logo.svg.png","slogan":"Sharing the World, Flying Together","head_quaters":"376, Hsin-Nan Rd., Sec. 1, Luzhu, Taoyuan City, Taiwan","website":"www.evaair.com","established":"1989"}],"__v":0,"_id":"98f73556-06fb-4129-ba01-226f2d614fc6"},"97514387-5a22-4633-904f-b5abd8cbcea8":{"name":"bane","trips":1,"airline":[{"id":5,"name":"Eva Air","country":"Taiwan","logo":"https://upload.wikimedia.org/wikipedia/en/thumb/e/ed/EVA_Air_logo.svg/250px-EVA_Air_logo.svg.png","slogan":"Sharing the World, Flying Together","head_quaters":"376, Hsin-Nan Rd., Sec. 1, Luzhu, Taoyuan City, Taiwan","website":"www.evaair.com","established":"1989"}],"__v":0,"_id":"97514387-5a22-4633-904f-b5abd8cbcea8"},"ac9cc248-482f-4165-b13a-65796139999e":{"name":"kjsg","trips":250,"airline":[{"id":5,"name":"Eva Air","country":"Taiwan","logo":"https://upload.wikimedia.org/wikipedia/en/thumb/e/ed/EVA_Air_logo.svg/250px-EVA_Air_logo.svg.png","slogan":"Sharing the World, Flying Together","head_quaters":"376, Hsin-Nan Rd., Sec. 1, Luzhu, Taoyuan City, Taiwan","website":"www.evaair.com","established":"1989"}],"__v":0,"_id":"ac9cc248-482f-4165-b13a-65796139999e"},"3f3a8c72-cdb2-4460-89a5-30cd033acda3":{"name":"kjsg","trips":250,"airline":[{"id":5,"name":"Eva Air","country":"Taiwan","logo":"https://upload.wikimedia.org/wikipedia/en/thumb/e/ed/EVA_Air_logo.svg/250px-EVA_Air_logo.svg.png","slogan":"Sharing the World, Flying Together","head_quaters":"376, Hsin-Nan Rd., Sec. 1, Luzhu, Taoyuan City, Taiwan","website":"www.evaair.com","established":"1989"}],"__v":0,"_id":"3f3a8c72-cdb2-4460-89a5-30cd033acda3"},"af511037-45d9-4b27-946a-d7c649f694ce":{"name":"kjsg","trips":250,"airline":[{"id":5,"name":"Eva Air","country":"Taiwan","logo":"https://upload.wikimedia.org/wikipedia/en/thumb/e/ed/EVA_Air_logo.svg/250px-EVA_Air_logo.svg.png","slogan":"Sharing the World, Flying Together","head_quaters":"376, Hsin-Nan Rd., Sec. 1, Luzhu, Taoyuan City, Taiwan","website":"www.evaair.com","established":"1989"}],"__v":0,"_id":"af511037-45d9-4b27-946a-d7c649f694ce"},"26ae1693-7bb2-4de8-8a37-87139efba882":{"_id":"26ae1693-7bb2-4de8-8a37-87139efba882","name":"kjsg","trips":250,"airline":[{"id":10,"name":"Eva Air","country":"Taiwan","logo":"https://upload.wikimedia.org/wikipedia/en/thumb/e/ed/EVA_Air_logo.svg/250px-EVA_Air_logo.svg.png","slogan":"Sharing the World, Flying Together","head_quaters":"376, Hsin-Nan Rd., Sec. 1, Luzhu, Taoyuan City, Taiwan","website":"www.evaair.com","established":"1989"}],"__v":1},"14c4bdb2-d945-4e0a-9c09-d786101daac9":{"name":"kjsg","trips":250,"airline":[{"id":5,"name":"Eva Air","country":"Taiwan","logo":"https://upload.wikimedia.org/wikipedia/en/thumb/e/ed/EVA_Air_logo.svg/250px-EVA_Air_logo.svg.png","slogan":"Sharing the World, Flying Together","head_quaters":"376, Hsin-Nan Rd., Sec. 1, Luzhu, Taoyuan City, Taiwan","website":"www.evaair.com","established":"1989"}],"__v":0,"_id":"14c4bdb2-d945-4e0a-9c09-d786101daac9"},"26e0a2bd-af41-45d1-9c44-5551bae6e066":{"name":"kjsg","trips":1,"airline":[{"id":5,"name":"Eva Air","country":"Taiwan","logo":"https://upload.wikimedia.org/wikipedia/en/thumb/e/ed/EVA_Air_logo.svg/250px-EVA_Air_logo.svg.png","slogan":"Sharing the World, Flying Together","head_quaters":"376, Hsin-Nan Rd., Sec. 1, Luzhu, Taoyuan City, Taiwan","website":"www.evaair.com","established":"1989"}],"__v":0,"_id":"26e0a2bd-af41-45d1-9c44-5551bae6e066"},"9441dfce-3144-4798-931a-684bf47fdb5a":{"name":"kjsg","trips":250,"airline":[{"id":5,"name":"Eva Air","country":"Taiwan","logo":"https://upload.wikimedia.org/wikipedia/en/thumb/e/ed/EVA_Air_logo.svg/250px-EVA_Air_logo.svg.png","slogan":"Sharing the World, Flying Together","head_quaters":"376, Hsin-Nan Rd., Sec. 1, Luzhu, Taoyuan City, Taiwan","website":"www.evaair.com","established":"1989"}],"__v":0,"_id":"9441dfce-3144-4798-931a-684bf47fdb5a"},"b4d1721e-0494-4520-aec7-578306f0515c":{"name":"kjsg","trips":1,"airline":[{"id":5,"name":"Eva Air","country":"Taiwan","logo":"https://upload.wikimedia.org/wikipedia/en/thumb/e/ed/EVA_Air_logo.svg/250px-EVA_Air_logo.svg.png","slogan":"Sharing the World, Flying Together","head_quaters":"376, Hsin-Nan Rd., Sec. 1, Luzhu, Taoyuan City, Taiwan","website":"www.evaair.com","established":"1989"}],"__v":0,"_id":"b4d1721e-0494-4520-aec7-578306f0515c"},"a78e46bf-8fd8-438b-ba5b-89ef21a40b37":{"name":"bane","trips":1,"airline":[{"id":5,"name":"Eva Air","country":"Taiwan","logo":"https://upload.wikimedia.org/wikipedia/en/thumb/e/ed/EVA_Air_logo.svg/250px-EVA_Air_logo.svg.png","slogan":"Sharing the World, Flying Together","head_quaters":"376, Hsin-Nan Rd., Sec. 1, Luzhu, Taoyuan City, Taiwan","website":"www.evaair.com","established":"1989"}],"__v":0,"_id":"a78e46bf-8fd8-438b-ba5b-89ef21a40b37"},"415dcca8-7d64-40fb-a8f8-e50021b06664":{"name":"kjsg","trips":250,"airline":[{"id":5,"name":"Eva Air","country":"Taiwan","logo":"https://upload.wikimedia.org/wikipedia/en/thumb/e/ed/EVA_Air_logo.svg/250px-EVA_Air_logo.svg.png","slogan":"Sharing the World, Flying Together","head_quaters":"376, Hsin-Nan Rd., Sec. 1, Luzhu, Taoyuan City, Taiwan","website":"www.evaair.com","established":"1989"}],"__v":0,"_id":"415dcca8-7d64-40fb-a8f8-e50021b06664"},"87e489ff-1a98-41e4-b569-7c41598fda1b":{"name":"kjsg","trips":250,"airline":[{"id":5,"name":"Eva Air","country":"Taiwan","logo":"https://upload.wikimedia.org/wikipedia/en/thumb/e/ed/EVA_Air_logo.svg/250px-EVA_Air_logo.svg.png","slogan":"Sharing the World, Flying Together","head_quaters":"376, Hsin-Nan Rd., Sec. 1, Luzhu, Taoyuan City, Taiwan","website":"www.evaair.com","established":"1989"}],"__v":0,"_id":"87e489ff-1a98-41e4-b569-7c41598fda1b"},"fd687692-df6b-4f6a-aae1-de7ea1a82eb6":{"name":"kjsg","trips":250,"airline":[{"id":5,"name":"Eva Air","country":"Taiwan","logo":"https://upload.wikimedia.org/wikipedia/en/thumb/e/ed/EVA_Air_logo.svg/250px-EVA_Air_logo.svg.png","slogan":"Sharing the World, Flying Together","head_quaters":"376, Hsin-Nan Rd., Sec. 1, Luzhu, Taoyuan City, Taiwan","website":"www.evaair.com","established":"1989"}],"__v":0,"_id":"fd687692-df6b-4f6a-aae1-de7ea1a82eb6"},"476e92b9-6064-44bb-9805-0bf740dcc4c0":{"_id":"476e92b9-6064-44bb-9805-0bf740dcc4c0","name":"kjsg","trips":250,"airline":[{"id":10,"name":"Eva Air","country":"Taiwan","logo":"https://upload.wikimedia.org/wikipedia/en/thumb/e/ed/EVA_Air_logo.svg/250px-EVA_Air_logo.svg.png","slogan":"Sharing the World, Flying Together","head_quaters":"376, Hsin-Nan Rd., Sec. 1, Luzhu, Taoyuan City, Taiwan","website":"www.evaair.com","established":"1989"}],"__v":1},"320eb4de-c07b-4ace-8224-02c5f6bd7d46":{"name":"kjsg","trips":250,"airline":[{"id":5,"name":"Eva Air","country":"Taiwan","logo":"https://upload.wikimedia.org/wikipedia/en/thumb/e/ed/EVA_Air_logo.svg/250px-EVA_Air_logo.svg.png","slogan":"Sharing the World, Flying Together","head_quaters":"376, Hsin-Nan Rd., Sec. 1, Luzhu, Taoyuan City, Taiwan","website":"www.evaair.com","established":"1989"}],"__v":0,"_id":"320eb4de-c07b-4ace-8224-02c5f6bd7d46"},"6e5788f6-e2e8-4c0f-9726-264862b504e5":{"name":"kjsg","trips":1,"airline":[{"id":5,"name":"Eva Air","country":"Taiwan","logo":"https://upload.wikimedia.org/wikipedia/en/thumb/e/ed/EVA_Air_logo.svg/250px-EVA_Air_logo.svg.png","slogan":"Sharing the World, Flying Together","head_quaters":"376, Hsin-Nan Rd., Sec. 1, Luzhu, Taoyuan City, Taiwan","website":"www.evaair.com","established":"1989"}],"__v":0,"_id":"6e5788f6-e2e8-4c0f-9726-264862b504e5"},"c123ac62-77b4-46a7-bd68-b705975497b6":{"name":"kjsg","trips":250,"airline":[{"id":5,"name":"Eva Air","country":"Taiwan","logo":"https://upload.wikimedia.org/wikipedia/en/thumb/e/ed/EVA_Air_logo.svg/250px-EVA_Air_logo.svg.png","slogan":"Sharing the World, Flying Together","head_quaters":"376, Hsin-Nan Rd., Sec. 1, Luzhu, Taoyuan City, Taiwan","website":"www.evaair.com","established":"1989"}],"__v":0,"_id":"c123ac62-77b4-46a7-bd68-b705975497b6"},"2847c9bb-cfc7-4cc3-a21d-bfb6a0fa82f0":{"name":"kjsg","trips":1,"airline":[{"id":5,"name":"Eva Air","country":"Taiwan","logo":"https://upload.wikimedia.org/wikipedia/en/thumb/e/ed/EVA_Air_logo.svg/250px-EVA_Air_logo.svg.png","slogan":"Sharing the World, Flying Together","head_quaters":"376, Hsin-Nan Rd., Sec. 1, Luzhu, Taoyuan City, Taiwan","website":"www.evaair.com","established":"1989"}],"__v":0,"_id":"2847c9bb-cfc7-4cc3-a21d-bfb6a0fa82f0"},"e482172a-e472-4606-8c1b-93ce9ac99b91":{"name":"bane","trips":1,"airline":[{"id":5,"name":"Eva Air","country":"Taiwan","logo":"https://upload.wikimedia.org/wikipedia/en/thumb/e/ed/EVA_Air_logo.svg/250px-EVA_Air_logo.svg.png","slogan":"Sharing the World, Flying Together","head_quaters":"376, Hsin-Nan Rd., Sec. 1, Luzhu, Taoyuan City, Taiwan","website":"www.evaair.com","established":"1989"}],"__v":0,"_id":"e482172a-e472-4606-8c1b-93ce9ac99b91"},"a172d36b-52c7-4a0d-ae69-0bff4c3f00c0":{"name":"kjsg","trips":250,"airline":[{"id":5,"name":"Eva Air","country":"Taiwan","logo":"https://upload.wikimedia.org/wikipedia/en/thumb/e/ed/EVA_Air_logo.svg/250px-EVA_Air_logo.svg.png","slogan":"Sharing the World, Flying Together","head_quaters":"376, Hsin-Nan Rd., Sec. 1, Luzhu, Taoyuan City, Taiwan","website":"www.evaair.com","established":"1989"}],"__v":0,"_id":"a172d36b-52c7-4a0d-ae69-0bff4c3f00c0"},"bd71bff8-b488-4e44-b97e-0eeeb0a78628":{"name":"kjsg","trips":250,"airline":[{"id":5,"name":"Eva Air","country":"Taiwan","logo":"https://upload.wikimedia.org/wikipedia/en/thumb/e/ed/EVA_Air_logo.svg/250px-EVA_Air_logo.svg.png","slogan":"Sharing the World, Flying Together","head_quaters":"376, Hsin-Nan Rd., Sec. 1, Luzhu, Taoyuan City, Taiwan","website":"www.evaair.com","established":"1989"}],"__v":0,"_id":"bd71bff8-b488-4e44-b97e-0eeeb0a78628"},"351734ce-c6c3-448a-8c99-bd371d21b8c2":{"name":"kjsg","trips":250,"airline":[{"id":5,"name":"Eva Air","country":"Taiwan","logo":"https://upload.wikimedia.org/wikipedia/en/thumb/e/ed/EVA_Air_logo.svg/250px-EVA_Air_logo.svg.png","slogan":"Sharing the World, Flying Together","head_quaters":"376, Hsin-Nan Rd., Sec. 1, Luzhu, Taoyuan City, Taiwan","website":"www.evaair.com","established":"1989"}],"__v":0,"_id":"351734ce-c6c3-448a-8c99-bd371d21b8c2"},"291888bf-c7d1-4717-a15a-27dad4c75f65":{"_id":"291888bf-c7d1-4717-a15a-27dad4c75f65","name":"kjsg","trips":250,"airline":[{"id":10,"name":"Eva Air","country":"Taiwan","logo":"https://upload.wikimedia.org/wikipedia/en/thumb/e/ed/EVA_Air_logo.svg/250px-EVA_Air_logo.svg.png","slogan":"Sharing the World, Flying Together","head_quaters":"376, Hsin-Nan Rd., Sec. 1, Luzhu, Taoyuan City, Taiwan","website":"www.evaair.com","established":"1989"}],"__v":1},"051ce5f4-b792-463c-8d23-df6283e0cb4c":{"name":"kjsg","trips":250,"airline":[{"id":5,"name":"Eva Air","country":"Taiwan","logo":"https://upload.wikimedia.org/wikipedia/en/thumb/e/ed/EVA_Air_logo.svg/250px-EVA_Air_logo.svg.png","slogan":"Sharing the World, Flying Together","head_quaters":"376, Hsin-Nan Rd., Sec. 1, Luzhu, Taoyuan City, Taiwan","website":"www.evaair.com","established":"1989"}],"__v":0,"_id":"051ce5f4-b792-463c-8d23-df6283e0cb4c"},"e2d39cdd-afb4-4652-a336-d8f5bd13b5e9":{"name":"kjsg","trips":1,"airline":[{"id":5,"name":"Eva Air","country":"Taiwan","logo":"https://upload.wikimedia.org/wikipedia/en/thumb/e/ed/EVA_Air_logo.svg/250px-EVA_Air_logo.svg.png","slogan":"Sharing the World, Flying Together","head_quaters":"376, Hsin-Nan Rd., Sec. 1, Luzhu, Taoyuan City, Taiwan","website":"www.evaair.com","established":"1989"}],"__v":0,"_id":"e2d39cdd-afb4-4652-a336-d8f5bd13b5e9"},"7c8d65a6-11c0-4609-8ac2-34d827da5648":{"name":"kjsg","trips":250,"airline":[{"id":5,"name":"Eva Air","country":"Taiwan","logo":"https://upload.wikimedia.org/wikipedia/en/thumb/e/ed/EVA_Air_logo.svg/250px-EVA_Air_logo.svg.png","slogan":"Sharing the World, Flying Together","head_quaters":"376, Hsin-Nan Rd., Sec. 1, Luzhu, Taoyuan City, Taiwan","website":"www.evaair.com","established":"1989"}],"__v":0,"_id":"7c8d65a6-11c0-4609-8ac2-34d827da5648"},"cb945bff-50a6-447e-a857-09d51ad776df":{"name":"kjsg","trips":1,"airline":[{"id":5,"name":"Eva Air","country":"Taiwan","logo":"https://upload.wikimedia.org/wikipedia/en/thumb/e/ed/EVA_Air_logo.svg/250px-EVA_Air_logo.svg.png","slogan":"Sharing the World, Flying Together","head_quaters":"376, Hsin-Nan Rd., Sec. 1, Luzhu, Taoyuan City, Taiwan","website":"www.evaair.com","established":"1989"}],"__v":0,"_id":"cb945bff-50a6-447e-a857-09d51ad776df"},"f28414c0-c280-4d0c-9911-889b14ed07c9":{"name":"bane","trips":1,"airline":[{"id":5,"name":"Eva Air","country":"Taiwan","logo":"https://upload.wikimedia.org/wikipedia/en/thumb/e/ed/EVA_Air_logo.svg/250px-EVA_Air_logo.svg.png","slogan":"Sharing the World, Flying Together","head_quaters":"376, Hsin-Nan Rd., Sec. 1, Luzhu, Taoyuan City, Taiwan","website":"www.evaair.com","established":"1989"}],"__v":0,"_id":"f28414c0-c280-4d0c-9911-889b14ed07c9"},"5efcdf5c-6d49-485c-ac94-44bd2e110703":{"name":"kjsg","trips":250,"airline":[{"id":5,"name":"Eva Air","country":"Taiwan","logo":"https://upload.wikimedia.org/wikipedia/en/thumb/e/ed/EVA_Air_logo.svg/250px-EVA_Air_logo.svg.png","slogan":"Sharing the World, Flying Together","head_quaters":"376, Hsin-Nan Rd., Sec. 1, Luzhu, Taoyuan City, Taiwan","website":"www.evaair.com","established":"1989"}],"__v":0,"_id":"5efcdf5c-6d49-485c-ac94-44bd2e110703"},"96c25b47-aaa8-42a5-97db-47162d5a29ec":{"name":"kjsg","trips":250,"airline":[{"id":5,"name":"Eva Air","country":"Taiwan","logo":"https://upload.wikimedia.org/wikipedia/en/thumb/e/ed/EVA_Air_logo.svg/250px-EVA_Air_logo.svg.png","slogan":"Sharing the World, Flying Together","head_quaters":"376, Hsin-Nan Rd., Sec. 1, Luzhu, Taoyuan City, Taiwan","website":"www.evaair.com","established":"1989"}],"__v":0,"_id":"96c25b47-aaa8-42a5-97db-47162d5a29ec"},"8ab2a3d5-8538-4cb8-8471-a997e6b2061b":{"name":"kjsg","trips":250,"airline":[{"id":5,"name":"Eva Air","country":"Taiwan","logo":"https://upload.wikimedia.org/wikipedia/en/thumb/e/ed/EVA_Air_logo.svg/250px-EVA_Air_logo.svg.png","slogan":"Sharing the World, Flying Together","head_quaters":"376, Hsin-Nan Rd., Sec. 1, Luzhu, Taoyuan City, Taiwan","website":"www.evaair.com","established":"1989"}],"__v":0,"_id":"8ab2a3d5-8538-4cb8-8471-a997e6b2061b"},"85276e9b-8507-4e60-8fc5-b158cde2fb5b":{"_id":"85276e9b-8507-4e60-8fc5-b158cde2fb5b","name":"kjsg","trips":250,"airline":[{"id":10,"name":"Eva Air","country":"Taiwan","logo":"https://upload.wikimedia.org/wikipedia/en/thumb/e/ed/EVA_Air_logo.svg/250px-EVA_Air_logo.svg.png","slogan":"Sharing the World, Flying Together","head_quaters":"376, Hsin-Nan Rd., Sec. 1, Luzhu, Taoyuan City, Taiwan","website":"www.evaair.com","established":"1989"}],"__v":1},"6853f36d-6d80-4bec-b48d-9b8bf64df48d":{"name":"kjsg","trips":250,"airline":[{"id":5,"name":"Eva Air","country":"Taiwan","logo":"https://upload.wikimedia.org/wikipedia/en/thumb/e/ed/EVA_Air_logo.svg/250px-EVA_Air_logo.svg.png","slogan":"Sharing the World, Flying Together","head_quaters":"376, Hsin-Nan Rd., Sec. 1, Luzhu, Taoyuan City, Taiwan","website":"www.evaair.com","established":"1989"}],"__v":0,"_id":"6853f36d-6d80-4bec-b48d-9b8bf64df48d"},"f87f35f0-cd06-4735-85ff-911f965cfb1d":{"name":"kjsg","trips":1,"airline":[{"id":5,"name":"Eva Air","country":"Taiwan","logo":"https://upload.wikimedia.org/wikipedia/en/thumb/e/ed/EVA_Air_logo.svg/250px-EVA_Air_logo.svg.png","slogan":"Sharing the World, Flying Together","head_quaters":"376, Hsin-Nan Rd., Sec. 1, Luzhu, Taoyuan City, Taiwan","website":"www.evaair.com","established":"1989"}],"__v":0,"_id":"f87f35f0-cd06-4735-85ff-911f965cfb1d"},"08597160-5561-4460-a3d2-e5f7d84d96be":{"name":"kjsg","trips":250,"airline":[{"id":5,"name":"Eva Air","country":"Taiwan","logo":"https://upload.wikimedia.org/wikipedia/en/thumb/e/ed/EVA_Air_logo.svg/250px-EVA_Air_logo.svg.png","slogan":"Sharing the World, Flying Together","head_quaters":"376, Hsin-Nan Rd., Sec. 1, Luzhu, Taoyuan City, Taiwan","website":"www.evaair.com","established":"1989"}],"__v":0,"_id":"08597160-5561-4460-a3d2-e5f7d84d96be"},"c03d5317-019f-45da-a306-cf89c57bed85":{"name":"kjsg","trips":1,"airline":[{"id":5,"name":"Eva Air","country":"Taiwan","logo":"https://upload.wikimedia.org/wikipedia/en/thumb/e/ed/EVA_Air_logo.svg/250px-EVA_Air_logo.svg.png","slogan":"Sharing the World, Flying Together","head_quaters":"376, Hsin-Nan Rd., Sec. 1, Luzhu, Taoyuan City, Taiwan","website":"www.evaair.com","established":"1989"}],"__v":0,"_id":"c03d5317-019f-45da-a306-cf89c57bed85"},"a731cc76-8391-46c8-b3d9-5fc8c44fec5f":{"name":"bane","trips":1,"airline":[{"id":5,"name":"Eva Air","country":"Taiwan","logo":"https://upload.wikimedia.org/wikipedia/en/thumb/e/ed/EVA_Air_logo.svg/250px-EVA_Air_logo.svg.png","slogan":"Sharing the World, Flying Together","head_quaters":"376, Hsin-Nan Rd., Sec. 1, Luzhu, Taoyuan City, Taiwan","website":"www.evaair.com","established":"1989"}],"__v":0,"_id":"a731cc76-8391-46c8-b3d9-5fc8c44fec5f"},"caef7072-b532-4f93-9e36-ecd540bd8906":{"name":"kjsg","trips":250,"airline":[{"id":5,"name":"Eva Air","country":"Taiwan","logo":"https://upload.wikimedia.org/wikipedia/en/thumb/e/ed/EVA_Air_logo.svg/250px-EVA_Air_logo.svg.png","slogan":"Sharing the World, Flying Together","head_quaters":"376, Hsin-Nan Rd., Sec. 1, Luzhu, Taoyuan City, Taiwan","website":"www.evaair.com","established":"1989"}],"__v":0,"_id":"caef7072-b532-4f93-9e36-ecd540bd8906"},"584d3bf2-f10e-4e1a-8624-a61a6caaec32":{"name":"kjsg","trips":250,"airline":[{"id":5,"name":"Eva Air","country":"Taiwan","logo":"https://upload.wikimedia.org/wikipedia/en/thumb/e/ed/EVA_Air_logo.svg/250px-EVA_Air_logo.svg.png","slogan":"Sharing the World, Flying Together","head_quaters":"376, Hsin-Nan Rd., Sec. 1, Luzhu, Taoyuan City, Taiwan","website":"www.evaair.com","established":"1989"}],"__v":0,"_id":"584d3bf2-f10e-4e1a-8624-a61a6caaec32"},"182ce85b-4b5a-4eac-b111-7647dddec992":{"name":"kjsg","trips":250,"airline":[{"id":5,"name":"Eva Air","country":"Taiwan","logo":"https://upload.wikimedia.org/wikipedia/en/thumb/e/ed/EVA_Air_logo.svg/250px-EVA_Air_logo.svg.png","slogan":"Sharing the World, Flying Together","head_quaters":"376, Hsin-Nan Rd., Sec. 1, Luzhu, Taoyuan City, Taiwan","website":"www.evaair.com","established":"1989"}],"__v":0,"_id":"182ce85b-4b5a-4eac-b111-7647dddec992"},"7821111b-b955-425f-99f6-ec546bf9db30":{"_id":"7821111b-b955-425f-99f6-ec546bf9db30","name":"kjsg","trips":250,"airline":[{"id":10,"name":"Eva Air","country":"Taiwan","logo":"https://upload.wikimedia.org/wikipedia/en/thumb/e/ed/EVA_Air_logo.svg/250px-EVA_Air_logo.svg.png","slogan":"Sharing the World, Flying Together","head_quaters":"376, Hsin-Nan Rd., Sec. 1, Luzhu, Taoyuan City, Taiwan","website":"www.evaair.com","established":"1989"}],"__v":1},"a4889ffd-ad81-4750-a8f2-dcd1dbe0a14b":{"name":"kjsg","trips":250,"airline":[{"id":5,"name":"Eva Air","country":"Taiwan","logo":"https://upload.wikimedia.org/wikipedia/en/thumb/e/ed/EVA_Air_logo.svg/250px-EVA_Air_logo.svg.png","slogan":"Sharing the World, Flying Together","head_quaters":"376, Hsin-Nan Rd., Sec. 1, Luzhu, Taoyuan City, Taiwan","website":"www.evaair.com","established":"1989"}],"__v":0,"_id":"a4889ffd-ad81-4750-a8f2-dcd1dbe0a14b"},"84ac2bce-dd52-433f-b154-f322e6770ee9":{"name":"kjsg","trips":1,"airline":[{"id":5,"name":"Eva Air","country":"Taiwan","logo":"https://upload.wikimedia.org/wikipedia/en/thumb/e/ed/EVA_Air_logo.svg/250px-EVA_Air_logo.svg.png","slogan":"Sharing the World, Flying Together","head_quaters":"376, Hsin-Nan Rd., Sec. 1, Luzhu, Taoyuan City, Taiwan","website":"www.evaair.com","established":"1989"}],"__v":0,"_id":"84ac2bce-dd52-433f-b154-f322e6770ee9"},"3f8b7f54-721d-4c2b-a6ba-86c9c0a5ed20":{"name":"kjsg","trips":250,"airline":[{"id":5,"name":"Eva Air","country":"Taiwan","logo":"https://upload.wikimedia.org/wikipedia/en/thumb/e/ed/EVA_Air_logo.svg/250px-EVA_Air_logo.svg.png","slogan":"Sharing the World, Flying Together","head_quaters":"376, Hsin-Nan Rd., Sec. 1, Luzhu, Taoyuan City, Taiwan","website":"www.evaair.com","established":"1989"}],"__v":0,"_id":"3f8b7f54-721d-4c2b-a6ba-86c9c0a5ed20"},"c4144d66-fd77-4073-a8d3-a139217c5caf":{"name":"kjsg","trips":1,"airline":[{"id":5,"name":"Eva Air","country":"Taiwan","logo":"https://upload.wikimedia.org/wikipedia/en/thumb/e/ed/EVA_Air_logo.svg/250px-EVA_Air_logo.svg.png","slogan":"Sharing the World, Flying Together","head_quaters":"376, Hsin-Nan Rd., Sec. 1, Luzhu, Taoyuan City, Taiwan","website":"www.evaair.com","established":"1989"}],"__v":0,"_id":"c4144d66-fd77-4073-a8d3-a139217c5caf"},"8bf55cc0-a767-4237-8e17-86517fa588b5":{"name":"bane","trips":1,"airline":[{"id":5,"name":"Eva Air","country":"Taiwan","logo":"https://upload.wikimedia.org/wikipedia/en/thumb/e/ed/EVA_Air_logo.svg/250px-EVA_Air_logo.svg.png","slogan":"Sharing the World, Flying Together","head_quaters":"376, Hsin-Nan Rd., Sec. 1, Luzhu, Taoyuan City, Taiwan","website":"www.evaair.com","established":"1989"}],"__v":0,"_id":"8bf55cc0-a767-4237-8e17-86517fa588b5"},"b30ae19d-885c-464a-93bd-4526fff80665":{"name":"kjsg","trips":250,"airline":[{"id":5,"name":"Eva Air","country":"Taiwan","logo":"https://upload.wikimedia.org/wikipedia/en/thumb/e/ed/EVA_Air_logo.svg/250px-EVA_Air_logo.svg.png","slogan":"Sharing the World, Flying Together","head_quaters":"376, Hsin-Nan Rd., Sec. 1, Luzhu, Taoyuan City, Taiwan","website":"www.evaair.com","established":"1989"}],"__v":0,"_id":"b30ae19d-885c-464a-93bd-4526fff80665"},"ae9c8751-56ec-4384-a5ee-45be302d8571":{"name":"kjsg","trips":250,"airline":[{"id":5,"name":"Eva Air","country":"Taiwan","logo":"https://upload.wikimedia.org/wikipedia/en/thumb/e/ed/EVA_Air_logo.svg/250px-EVA_Air_logo.svg.png","slogan":"Sharing the World, Flying Together","head_quaters":"376, Hsin-Nan Rd., Sec. 1, Luzhu, Taoyuan City, Taiwan","website":"www.evaair.com","established":"1989"}],"__v":0,"_id":"ae9c8751-56ec-4384-a5ee-45be302d8571"},"fb3c7e7a-6898-4a25-9d5c-0ff97695d1ef":{"name":"kjsg","trips":250,"airline":[{"id":5,"name":"Eva Air","country":"Taiwan","logo":"https://upload.wikimedia.org/wikipedia/en/thumb/e/ed/EVA_Air_logo.svg/250px-EVA_Air_logo.svg.png","slogan":"Sharing the World, Flying Together","head_quaters":"376, Hsin-Nan Rd., Sec. 1, Luzhu, Taoyuan City, Taiwan","website":"www.evaair.com","established":"1989"}],"__v":0,"_id":"fb3c7e7a-6898-4a25-9d5c-0ff97695d1ef"},"dd4f40bf-61e1-4494-9b7e-e1efd7d92d21":{"_id":"dd4f40bf-61e1-4494-9b7e-e1efd7d92d21","name":"kjsg","trips":250,"airline":[{"id":10,"name":"Eva Air","country":"Taiwan","logo":"https://upload.wikimedia.org/wikipedia/en/thumb/e/ed/EVA_Air_logo.svg/250px-EVA_Air_logo.svg.png","slogan":"Sharing the World, Flying Together","head_quaters":"376, Hsin-Nan Rd., Sec. 1, Luzhu, Taoyuan City, Taiwan","website":"www.evaair.com","established":"1989"}],"__v":1},"91983cf7-ebdb-421f-adbd-459cde5066e5":{"name":"kjsg","trips":250,"airline":[{"id":5,"name":"Eva Air","country":"Taiwan","logo":"https://upload.wikimedia.org/wikipedia/en/thumb/e/ed/EVA_Air_logo.svg/250px-EVA_Air_logo.svg.png","slogan":"Sharing the World, Flying Together","head_quaters":"376, Hsin-Nan Rd., Sec. 1, Luzhu, Taoyuan City, Taiwan","website":"www.evaair.com","established":"1989"}],"__v":0,"_id":"91983cf7-ebdb-421f-adbd-459cde5066e5"},"6efb895f-db6f-4af7-aa7d-95163ec127e8":{"name":"kjsg","trips":1,"airline":[{"id":5,"name":"Eva Air","country":"Taiwan","logo":"https://upload.wikimedia.org/wikipedia/en/thumb/e/ed/EVA_Air_logo.svg/250px-EVA_Air_logo.svg.png","slogan":"Sharing the World, Flying Together","head_quaters":"376, Hsin-Nan Rd., Sec. 1, Luzhu, Taoyuan City, Taiwan","website":"www.evaair.com","established":"1989"}],"__v":0,"_id":"6efb895f-db6f-4af7-aa7d-95163ec127e8"},"8893cf82-9fb1-44c6-a8b4-9a73d90124c6":{"name":"kjsg","trips":250,"airline":[{"id":5,"name":"Eva Air","country":"Taiwan","logo":"https://upload.wikimedia.org/wikipedia/en/thumb/e/ed/EVA_Air_logo.svg/250px-EVA_Air_logo.svg.png","slogan":"Sharing the World, Flying Together","head_quaters":"376, Hsin-Nan Rd., Sec. 1, Luzhu, Taoyuan City, Taiwan","website":"www.evaair.com","established":"1989"}],"__v":0,"_id":"8893cf82-9fb1-44c6-a8b4-9a73d90124c6"},"3fa153d7-051c-495b-9dcd-e0f8025372c7":{"name":"kjsg","trips":250,"airline":[{"id":5,"name":"Eva Air","country":"Taiwan","logo":"https://upload.wikimedia.org/wikipedia/en/thumb/e/ed/EVA_Air_logo.svg/250px-EVA_Air_logo.svg.png","slogan":"Sharing the World, Flying Together","head_quaters":"376, Hsin-Nan Rd., Sec. 1, Luzhu, Taoyuan City, Taiwan","website":"www.evaair.com","established":"1989"}],"__v":0,"_id":"3fa153d7-051c-495b-9dcd-e0f8025372c7"},"44d0721c-9b02-4a71-a39c-da4e1b7c9e42":{"name":"kjsg","trips":250,"airline":[{"id":5,"name":"Eva Air","country":"Taiwan","logo":"https://upload.wikimedia.org/wikipedia/en/thumb/e/ed/EVA_Air_logo.svg/250px-EVA_Air_logo.svg.png","slogan":"Sharing the World, Flying Together","head_quaters":"376, Hsin-Nan Rd., Sec. 1, Luzhu, Taoyuan City, Taiwan","website":"www.evaair.com","established":"1989"}],"__v":0,"_id":"44d0721c-9b02-4a71-a39c-da4e1b7c9e42"},"d0c97886-8c60-4fb8-93e8-78f4105bc73e":{"name":"kjsg","trips":250,"airline":[{"id":5,"name":"Eva Air","country":"Taiwan","logo":"https://upload.wikimedia.org/wikipedia/en/thumb/e/ed/EVA_Air_logo.svg/250px-EVA_Air_logo.svg.png","slogan":"Sharing the World, Flying Together","head_quaters":"376, Hsin-Nan Rd., Sec. 1, Luzhu, Taoyuan City, Taiwan","website":"www.evaair.com","established":"1989"}],"__v":0,"_id":"d0c97886-8c60-4fb8-93e8-78f4105bc73e"},"04d9e49f-81a6-4b80-ae4f-487af0207f44":{"name":"kjsg","trips":250,"airline":[{"id":5,"name":"Eva Air","country":"Taiwan","logo":"https://upload.wikimedia.org/wikipedia/en/thumb/e/ed/EVA_Air_logo.svg/250px-EVA_Air_logo.svg.png","slogan":"Sharing the World, Flying Together","head_quaters":"376, Hsin-Nan Rd., Sec. 1, Luzhu, Taoyuan City, Taiwan","website":"www.evaair.com","established":"1989"}],"__v":0,"_id":"04d9e49f-81a6-4b80-ae4f-487af0207f44"},"dfebe10f-9664-47f0-96db-2b662a31ac12":{"name":"kjsg","trips":250,"airline":[{"id":5,"name":"Eva Air","country":"Taiwan","logo":"https://upload.wikimedia.org/wikipedia/en/thumb/e/ed/EVA_Air_logo.svg/250px-EVA_Air_logo.svg.png","slogan":"Sharing the World, Flying Together","head_quaters":"376, Hsin-Nan Rd., Sec. 1, Luzhu, Taoyuan City, Taiwan","website":"www.evaair.com","established":"1989"}],"__v":0,"_id":"dfebe10f-9664-47f0-96db-2b662a31ac12"},"3ca6f46e-06cf-4c35-924b-54a6e09998a9":{"name":"kjsg","trips":250,"airline":[{"id":5,"name":"Eva Air","country":"Taiwan","logo":"https://upload.wikimedia.org/wikipedia/en/thumb/e/ed/EVA_Air_logo.svg/250px-EVA_Air_logo.svg.png","slogan":"Sharing the World, Flying Together","head_quaters":"376, Hsin-Nan Rd., Sec. 1, Luzhu, Taoyuan City, Taiwan","website":"www.evaair.com","established":"1989"}],"__v":0,"_id":"3ca6f46e-06cf-4c35-924b-54a6e09998a9"},"23356c38-8fed-4f22-84d0-32f3ccac8992":{"_id":"23356c38-8fed-4f22-84d0-32f3ccac8992","name":"kjsg","trips":250,"airline":[{"id":10,"name":"Eva Air","country":"Taiwan","logo":"https://upload.wikimedia.org/wikipedia/en/thumb/e/ed/EVA_Air_logo.svg/250px-EVA_Air_logo.svg.png","slogan":"Sharing the World, Flying Together","head_quaters":"376, Hsin-Nan Rd., Sec. 1, Luzhu, Taoyuan City, Taiwan","website":"www.evaair.com","established":"1989"}],"__v":1},"bece9170-e3be-4483-b551-ead6a4694bc5":{"name":"kjsg","trips":250,"airline":[{"id":5,"name":"Eva Air","country":"Taiwan","logo":"https://upload.wikimedia.org/wikipedia/en/thumb/e/ed/EVA_Air_logo.svg/250px-EVA_Air_logo.svg.png","slogan":"Sharing the World, Flying Together","head_quaters":"376, Hsin-Nan Rd., Sec. 1, Luzhu, Taoyuan City, Taiwan","website":"www.evaair.com","established":"1989"}],"__v":0,"_id":"bece9170-e3be-4483-b551-ead6a4694bc5"},"e6007628-3581-4b02-87fb-1d5e4170ac4c":{"name":"kjsg","trips":1,"airline":[{"id":5,"name":"Eva Air","country":"Taiwan","logo":"https://upload.wikimedia.org/wikipedia/en/thumb/e/ed/EVA_Air_logo.svg/250px-EVA_Air_logo.svg.png","slogan":"Sharing the World, Flying Together","head_quaters":"376, Hsin-Nan Rd., Sec. 1, Luzhu, Taoyuan City, Taiwan","website":"www.evaair.com","established":"1989"}],"__v":0,"_id":"e6007628-3581-4b02-87fb-1d5e4170ac4c"},"94d736c0-2977-4670-a933-736d5bc43879":{"name":"kjsg","trips":250,"airline":[{"id":5,"name":"Eva Air","country":"Taiwan","logo":"https://upload.wikimedia.org/wikipedia/en/thumb/e/ed/EVA_Air_logo.svg/250px-EVA_Air_logo.svg.png","slogan":"Sharing the World, Flying Together","head_quaters":"376, Hsin-Nan Rd., Sec. 1, Luzhu, Taoyuan City, Taiwan","website":"www.evaair.com","established":"1989"}],"__v":0,"_id":"94d736c0-2977-4670-a933-736d5bc43879"},"5b72e614-fdc9-4f52-b4fe-abd6b3116417":{"name":"kjsg","trips":250,"airline":[{"id":5,"name":"Eva Air","country":"Taiwan","logo":"https://upload.wikimedia.org/wikipedia/en/thumb/e/ed/EVA_Air_logo.svg/250px-EVA_Air_logo.svg.png","slogan":"Sharing the World, Flying Together","head_quaters":"376, Hsin-Nan Rd., Sec. 1, Luzhu, Taoyuan City, Taiwan","website":"www.evaair.com","established":"1989"}],"__v":0,"_id":"5b72e614-fdc9-4f52-b4fe-abd6b3116417"},"e6d89e7b-eeb0-4a53-8109-ca85704ebd29":{"name":"kjsg","trips":250,"airline":[{"id":5,"name":"Eva Air","country":"Taiwan","logo":"https://upload.wikimedia.org/wikipedia/en/thumb/e/ed/EVA_Air_logo.svg/250px-EVA_Air_logo.svg.png","slogan":"Sharing the World, Flying Together","head_quaters":"376, Hsin-Nan Rd., Sec. 1, Luzhu, Taoyuan City, Taiwan","website":"www.evaair.com","established":"1989"}],"__v":0,"_id":"e6d89e7b-eeb0-4a53-8109-ca85704ebd29"},"7c1a96a9-9fcc-4ae8-bc0e-f40479286fbe":{"name":"kjsg","trips":250,"airline":[{"id":5,"name":"Eva Air","country":"Taiwan","logo":"https://upload.wikimedia.org/wikipedia/en/thumb/e/ed/EVA_Air_logo.svg/250px-EVA_Air_logo.svg.png","slogan":"Sharing the World, Flying Together","head_quaters":"376, Hsin-Nan Rd., Sec. 1, Luzhu, Taoyuan City, Taiwan","website":"www.evaair.com","established":"1989"}],"__v":0,"_id":"7c1a96a9-9fcc-4ae8-bc0e-f40479286fbe"},"33dabb6e-f10f-48ed-8e9a-d642a29415f2":{"name":"kjsg","trips":250,"airline":[{"id":5,"name":"Eva Air","country":"Taiwan","logo":"https://upload.wikimedia.org/wikipedia/en/thumb/e/ed/EVA_Air_logo.svg/250px-EVA_Air_logo.svg.png","slogan":"Sharing the World, Flying Together","head_quaters":"376, Hsin-Nan Rd., Sec. 1, Luzhu, Taoyuan City, Taiwan","website":"www.evaair.com","established":"1989"}],"__v":0,"_id":"33dabb6e-f10f-48ed-8e9a-d642a29415f2"},"3f47fecd-85ca-425a-ac3f-e42174440979":{"name":"kjsg","trips":250,"airline":[{"id":5,"name":"Eva Air","country":"Taiwan","logo":"https://upload.wikimedia.org/wikipedia/en/thumb/e/ed/EVA_Air_logo.svg/250px-EVA_Air_logo.svg.png","slogan":"Sharing the World, Flying Together","head_quaters":"376, Hsin-Nan Rd., Sec. 1, Luzhu, Taoyuan City, Taiwan","website":"www.evaair.com","established":"1989"}],"__v":0,"_id":"3f47fecd-85ca-425a-ac3f-e42174440979"},"6d531c6e-01c9-4d6c-95f9-db192b7ef8c6":{"name":"kjsg","trips":250,"airline":[{"id":5,"name":"Eva Air","country":"Taiwan","logo":"https://upload.wikimedia.org/wikipedia/en/thumb/e/ed/EVA_Air_logo.svg/250px-EVA_Air_logo.svg.png","slogan":"Sharing the World, Flying Together","head_quaters":"376, Hsin-Nan Rd., Sec. 1, Luzhu, Taoyuan City, Taiwan","website":"www.evaair.com","established":"1989"}],"__v":0,"_id":"6d531c6e-01c9-4d6c-95f9-db192b7ef8c6"},"8f27eb8f-6fe3-4905-a394-f9012f629265":{"_id":"8f27eb8f-6fe3-4905-a394-f9012f629265","name":"kjsg","trips":250,"airline":[{"id":10,"name":"Eva Air","country":"Taiwan","logo":"https://upload.wikimedia.org/wikipedia/en/thumb/e/ed/EVA_Air_logo.svg/250px-EVA_Air_logo.svg.png","slogan":"Sharing the World, Flying Together","head_quaters":"376, Hsin-Nan Rd., Sec. 1, Luzhu, Taoyuan City, Taiwan","website":"www.evaair.com","established":"1989"}],"__v":1},"6796a709-6d45-41a6-86e5-6e8f34a6fd3b":{"name":"kjsg","trips":250,"airline":[{"id":5,"name":"Eva Air","country":"Taiwan","logo":"https://upload.wikimedia.org/wikipedia/en/thumb/e/ed/EVA_Air_logo.svg/250px-EVA_Air_logo.svg.png","slogan":"Sharing the World, Flying Together","head_quaters":"376, Hsin-Nan Rd., Sec. 1, Luzhu, Taoyuan City, Taiwan","website":"www.evaair.com","established":"1989"}],"__v":0,"_id":"6796a709-6d45-41a6-86e5-6e8f34a6fd3b"},"fbe55346-6410-40cb-a32f-6fb9ef64f716":{"name":"kjsg","trips":1,"airline":[{"id":5,"name":"Eva Air","country":"Taiwan","logo":"https://upload.wikimedia.org/wikipedia/en/thumb/e/ed/EVA_Air_logo.svg/250px-EVA_Air_logo.svg.png","slogan":"Sharing the World, Flying Together","head_quaters":"376, Hsin-Nan Rd., Sec. 1, Luzhu, Taoyuan City, Taiwan","website":"www.evaair.com","established":"1989"}],"__v":0,"_id":"fbe55346-6410-40cb-a32f-6fb9ef64f716"},"f45698cf-0766-49cc-80a4-9688ff4f896e":{"name":"kjsg","trips":250,"airline":[{"id":5,"name":"Eva Air","country":"Taiwan","logo":"https://upload.wikimedia.org/wikipedia/en/thumb/e/ed/EVA_Air_logo.svg/250px-EVA_Air_logo.svg.png","slogan":"Sharing the World, Flying Together","head_quaters":"376, Hsin-Nan Rd., Sec. 1, Luzhu, Taoyuan City, Taiwan","website":"www.evaair.com","established":"1989"}],"__v":0,"_id":"f45698cf-0766-49cc-80a4-9688ff4f896e"},"90a2c564-f540-4d09-bb18-7e69e8a4f248":{"name":"kjsg","trips":250,"airline":[{"id":5,"name":"Eva Air","country":"Taiwan","logo":"https://upload.wikimedia.org/wikipedia/en/thumb/e/ed/EVA_Air_logo.svg/250px-EVA_Air_logo.svg.png","slogan":"Sharing the World, Flying Together","head_quaters":"376, Hsin-Nan Rd., Sec. 1, Luzhu, Taoyuan City, Taiwan","website":"www.evaair.com","established":"1989"}],"__v":0,"_id":"90a2c564-f540-4d09-bb18-7e69e8a4f248"},"557b7cb5-447a-4bd4-95a1-354ce9bb775d":{"name":"kjsg","trips":250,"airline":[{"id":5,"name":"Eva Air","country":"Taiwan","logo":"https://upload.wikimedia.org/wikipedia/en/thumb/e/ed/EVA_Air_logo.svg/250px-EVA_Air_logo.svg.png","slogan":"Sharing the World, Flying Together","head_quaters":"376, Hsin-Nan Rd., Sec. 1, Luzhu, Taoyuan City, Taiwan","website":"www.evaair.com","established":"1989"}],"__v":0,"_id":"557b7cb5-447a-4bd4-95a1-354ce9bb775d"},"613be4a6-872c-4359-b859-b2e562543629":{"name":"kjsg","trips":250,"airline":[{"id":5,"name":"Eva Air","country":"Taiwan","logo":"https://upload.wikimedia.org/wikipedia/en/thumb/e/ed/EVA_Air_logo.svg/250px-EVA_Air_logo.svg.png","slogan":"Sharing the World, Flying Together","head_quaters":"376, Hsin-Nan Rd., Sec. 1, Luzhu, Taoyuan City, Taiwan","website":"www.evaair.com","established":"1989"}],"__v":0,"_id":"613be4a6-872c-4359-b859-b2e562543629"},"f0558d86-a63d-451b-8e38-c72f19ed1679":{"name":"kjsg","trips":250,"airline":[{"id":5,"name":"Eva Air","country":"Taiwan","logo":"https://upload.wikimedia.org/wikipedia/en/thumb/e/ed/EVA_Air_logo.svg/250px-EVA_Air_logo.svg.png","slogan":"Sharing the World, Flying Together","head_quaters":"376, Hsin-Nan Rd., Sec. 1, Luzhu, Taoyuan City, Taiwan","website":"www.evaair.com","established":"1989"}],"__v":0,"_id":"f0558d86-a63d-451b-8e38-c72f19ed1679"},"49e885d7-b212-4c28-acb6-439b746054d3":{"name":"kjsg","trips":250,"airline":[{"id":5,"name":"Eva Air","country":"Taiwan","logo":"https://upload.wikimedia.org/wikipedia/en/thumb/e/ed/EVA_Air_logo.svg/250px-EVA_Air_logo.svg.png","slogan":"Sharing the World, Flying Together","head_quaters":"376, Hsin-Nan Rd., Sec. 1, Luzhu, Taoyuan City, Taiwan","website":"www.evaair.com","established":"1989"}],"__v":0,"_id":"49e885d7-b212-4c28-acb6-439b746054d3"},"1a35513b-23b2-4c8c-b305-b8fbcc183016":{"name":"kjsg","trips":250,"airline":[{"id":5,"name":"Eva Air","country":"Taiwan","logo":"https://upload.wikimedia.org/wikipedia/en/thumb/e/ed/EVA_Air_logo.svg/250px-EVA_Air_logo.svg.png","slogan":"Sharing the World, Flying Together","head_quaters":"376, Hsin-Nan Rd., Sec. 1, Luzhu, Taoyuan City, Taiwan","website":"www.evaair.com","established":"1989"}],"__v":0,"_id":"1a35513b-23b2-4c8c-b305-b8fbcc183016"},"e342d660-e019-4731-8492-2bc0615f9025":{"_id":"e342d660-e019-4731-8492-2bc0615f9025","name":"kjsg","trips":250,"airline":[{"id":10,"name":"Eva Air","country":"Taiwan","logo":"https://upload.wikimedia.org/wikipedia/en/thumb/e/ed/EVA_Air_logo.svg/250px-EVA_Air_logo.svg.png","slogan":"Sharing the World, Flying Together","head_quaters":"376, Hsin-Nan Rd., Sec. 1, Luzhu, Taoyuan City, Taiwan","website":"www.evaair.com","established":"1989"}],"__v":1},"e1a35f34-218c-4820-9509-5d88b3c3e311":{"name":"kjsg","trips":250,"airline":[{"id":5,"name":"Eva Air","country":"Taiwan","logo":"https://upload.wikimedia.org/wikipedia/en/thumb/e/ed/EVA_Air_logo.svg/250px-EVA_Air_logo.svg.png","slogan":"Sharing the World, Flying Together","head_quaters":"376, Hsin-Nan Rd., Sec. 1, Luzhu, Taoyuan City, Taiwan","website":"www.evaair.com","established":"1989"}],"__v":0,"_id":"e1a35f34-218c-4820-9509-5d88b3c3e311"},"483ff2ff-fbc4-4bfa-89a6-36c04af94ac6":{"name":"kjsg","trips":1,"airline":[{"id":5,"name":"Eva Air","country":"Taiwan","logo":"https://upload.wikimedia.org/wikipedia/en/thumb/e/ed/EVA_Air_logo.svg/250px-EVA_Air_logo.svg.png","slogan":"Sharing the World, Flying Together","head_quaters":"376, Hsin-Nan Rd., Sec. 1, Luzhu, Taoyuan City, Taiwan","website":"www.evaair.com","established":"1989"}],"__v":0,"_id":"483ff2ff-fbc4-4bfa-89a6-36c04af94ac6"},"7342d19c-c134-4e08-a9af-be41684b1574":{"name":"kjsg","trips":250,"airline":[{"id":5,"name":"Eva Air","country":"Taiwan","logo":"https://upload.wikimedia.org/wikipedia/en/thumb/e/ed/EVA_Air_logo.svg/250px-EVA_Air_logo.svg.png","slogan":"Sharing the World, Flying Together","head_quaters":"376, Hsin-Nan Rd., Sec. 1, Luzhu, Taoyuan City, Taiwan","website":"www.evaair.com","established":"1989"}],"__v":0,"_id":"7342d19c-c134-4e08-a9af-be41684b1574"},"787f36b2-28af-4286-8e7b-645a1ee48700":{"name":"kjsg","trips":250,"airline":[{"id":5,"name":"Eva Air","country":"Taiwan","logo":"https://upload.wikimedia.org/wikipedia/en/thumb/e/ed/EVA_Air_logo.svg/250px-EVA_Air_logo.svg.png","slogan":"Sharing the World, Flying Together","head_quaters":"376, Hsin-Nan Rd., Sec. 1, Luzhu, Taoyuan City, Taiwan","website":"www.evaair.com","established":"1989"}],"__v":0,"_id":"787f36b2-28af-4286-8e7b-645a1ee48700"},"10594910-d5bc-42e0-b20f-9412b0bc4e56":{"name":"kjsg","trips":250,"airline":[{"id":5,"name":"Eva Air","country":"Taiwan","logo":"https://upload.wikimedia.org/wikipedia/en/thumb/e/ed/EVA_Air_logo.svg/250px-EVA_Air_logo.svg.png","slogan":"Sharing the World, Flying Together","head_quaters":"376, Hsin-Nan Rd., Sec. 1, Luzhu, Taoyuan City, Taiwan","website":"www.evaair.com","established":"1989"}],"__v":0,"_id":"10594910-d5bc-42e0-b20f-9412b0bc4e56"},"8803445e-84c8-4d06-84e3-4d7dc3d72137":{"name":"kjsg","trips":250,"airline":[{"id":5,"name":"Eva Air","country":"Taiwan","logo":"https://upload.wikimedia.org/wikipedia/en/thumb/e/ed/EVA_Air_logo.svg/250px-EVA_Air_logo.svg.png","slogan":"Sharing the World, Flying Together","head_quaters":"376, Hsin-Nan Rd., Sec. 1, Luzhu, Taoyuan City, Taiwan","website":"www.evaair.com","established":"1989"}],"__v":0,"_id":"8803445e-84c8-4d06-84e3-4d7dc3d72137"},"e6d4914b-780a-47e3-b4c4-ce922dec0efc":{"name":"kjsg","trips":250,"airline":[{"id":5,"name":"Eva Air","country":"Taiwan","logo":"https://upload.wikimedia.org/wikipedia/en/thumb/e/ed/EVA_Air_logo.svg/250px-EVA_Air_logo.svg.png","slogan":"Sharing the World, Flying Together","head_quaters":"376, Hsin-Nan Rd., Sec. 1, Luzhu, Taoyuan City, Taiwan","website":"www.evaair.com","established":"1989"}],"__v":0,"_id":"e6d4914b-780a-47e3-b4c4-ce922dec0efc"},"abc1ee79-284a-4d36-bd17-03555b743e34":{"name":"kjsg","trips":250,"airline":[{"id":5,"name":"Eva Air","country":"Taiwan","logo":"https://upload.wikimedia.org/wikipedia/en/thumb/e/ed/EVA_Air_logo.svg/250px-EVA_Air_logo.svg.png","slogan":"Sharing the World, Flying Together","head_quaters":"376, Hsin-Nan Rd., Sec. 1, Luzhu, Taoyuan City, Taiwan","website":"www.evaair.com","established":"1989"}],"__v":0,"_id":"abc1ee79-284a-4d36-bd17-03555b743e34"},"52a176de-3e41-4a12-82e0-5c0f13d72396":{"name":"kjsg","trips":250,"airline":[{"id":5,"name":"Eva Air","country":"Taiwan","logo":"https://upload.wikimedia.org/wikipedia/en/thumb/e/ed/EVA_Air_logo.svg/250px-EVA_Air_logo.svg.png","slogan":"Sharing the World, Flying Together","head_quaters":"376, Hsin-Nan Rd., Sec. 1, Luzhu, Taoyuan City, Taiwan","website":"www.evaair.com","established":"1989"}],"__v":0,"_id":"52a176de-3e41-4a12-82e0-5c0f13d72396"},"4913452f-d811-402d-9ce2-f140840c974e":{"_id":"4913452f-d811-402d-9ce2-f140840c974e","name":"kjsg","trips":250,"airline":[{"id":10,"name":"Eva Air","country":"Taiwan","logo":"https://upload.wikimedia.org/wikipedia/en/thumb/e/ed/EVA_Air_logo.svg/250px-EVA_Air_logo.svg.png","slogan":"Sharing the World, Flying Together","head_quaters":"376, Hsin-Nan Rd., Sec. 1, Luzhu, Taoyuan City, Taiwan","website":"www.evaair.com","established":"1989"}],"__v":1},"71b5249f-1885-4eb3-a91b-fa4a9b6c053f":{"name":"kjsg","trips":250,"airline":[{"id":5,"name":"Eva Air","country":"Taiwan","logo":"https://upload.wikimedia.org/wikipedia/en/thumb/e/ed/EVA_Air_logo.svg/250px-EVA_Air_logo.svg.png","slogan":"Sharing the World, Flying Together","head_quaters":"376, Hsin-Nan Rd., Sec. 1, Luzhu, Taoyuan City, Taiwan","website":"www.evaair.com","established":"1989"}],"__v":0,"_id":"71b5249f-1885-4eb3-a91b-fa4a9b6c053f"},"fc676955-199a-4571-86d4-e6f5b9de080c":{"name":"kjsg","trips":1,"airline":[{"id":5,"name":"Eva Air","country":"Taiwan","logo":"https://upload.wikimedia.org/wikipedia/en/thumb/e/ed/EVA_Air_logo.svg/250px-EVA_Air_logo.svg.png","slogan":"Sharing the World, Flying Together","head_quaters":"376, Hsin-Nan Rd., Sec. 1, Luzhu, Taoyuan City, Taiwan","website":"www.evaair.com","established":"1989"}],"__v":0,"_id":"fc676955-199a-4571-86d4-e6f5b9de080c"},"6b19a901-1fbd-4d4d-876d-b681736f624a":{"name":"kjsg","trips":250,"airline":[{"id":5,"name":"Eva Air","country":"Taiwan","logo":"https://upload.wikimedia.org/wikipedia/en/thumb/e/ed/EVA_Air_logo.svg/250px-EVA_Air_logo.svg.png","slogan":"Sharing the World, Flying Together","head_quaters":"376, Hsin-Nan Rd., Sec. 1, Luzhu, Taoyuan City, Taiwan","website":"www.evaair.com","established":"1989"}],"__v":0,"_id":"6b19a901-1fbd-4d4d-876d-b681736f624a"},"70a7568a-bfee-4e79-a0ff-ed20b90ca2e7":{"name":"kjsg","trips":250,"airline":[{"id":5,"name":"Eva Air","country":"Taiwan","logo":"https://upload.wikimedia.org/wikipedia/en/thumb/e/ed/EVA_Air_logo.svg/250px-EVA_Air_logo.svg.png","slogan":"Sharing the World, Flying Together","head_quaters":"376, Hsin-Nan Rd., Sec. 1, Luzhu, Taoyuan City, Taiwan","website":"www.evaair.com","established":"1989"}],"__v":0,"_id":"70a7568a-bfee-4e79-a0ff-ed20b90ca2e7"},"41cbb0b9-a84e-4804-9462-0a6bb11d844e":{"name":"kjsg","trips":250,"airline":[{"id":5,"name":"Eva Air","country":"Taiwan","logo":"https://upload.wikimedia.org/wikipedia/en/thumb/e/ed/EVA_Air_logo.svg/250px-EVA_Air_logo.svg.png","slogan":"Sharing the World, Flying Together","head_quaters":"376, Hsin-Nan Rd., Sec. 1, Luzhu, Taoyuan City, Taiwan","website":"www.evaair.com","established":"1989"}],"__v":0,"_id":"41cbb0b9-a84e-4804-9462-0a6bb11d844e"},"047be098-73d5-4d3f-8560-b53645e8d0fb":{"name":"kjsg","trips":250,"airline":[{"id":5,"name":"Eva Air","country":"Taiwan","logo":"https://upload.wikimedia.org/wikipedia/en/thumb/e/ed/EVA_Air_logo.svg/250px-EVA_Air_logo.svg.png","slogan":"Sharing the World, Flying Together","head_quaters":"376, Hsin-Nan Rd., Sec. 1, Luzhu, Taoyuan City, Taiwan","website":"www.evaair.com","established":"1989"}],"__v":0,"_id":"047be098-73d5-4d3f-8560-b53645e8d0fb"},"326860b4-be0c-4ae4-ae16-14a1f196d872":{"name":"Danika Danika","trips":250,"airline":[{"id":5,"name":"Eva Air","country":"Taiwan","logo":"https://upload.wikimedia.org/wikipedia/en/thumb/e/ed/EVA_Air_logo.svg/250px-EVA_Air_logo.svg.png","slogan":"Sharing the World, Flying Together","head_quaters":"376, Hsin-Nan Rd., Sec. 1, Luzhu, Taoyuan City, Taiwan","website":"www.evaair.com","established":"1989"}],"__v":0,"_id":"326860b4-be0c-4ae4-ae16-14a1f196d872"},"5b77c8b2-797f-47e4-b9fa-b97a7950f01c":{"name":"Danika Danika","trips":250,"airline":[{"id":5,"name":"Eva Air","country":"Taiwan","logo":"https://upload.wikimedia.org/wikipedia/en/thumb/e/ed/EVA_Air_logo.svg/250px-EVA_Air_logo.svg.png","slogan":"Sharing the World, Flying Together","head_quaters":"376, Hsin-Nan Rd., Sec. 1, Luzhu, Taoyuan City, Taiwan","website":"www.evaair.com","established":"1989"}],"__v":0,"_id":"5b77c8b2-797f-47e4-b9fa-b97a7950f01c"},"b86ba361-fb9a-44b6-961c-7ec78d18fea8":{"name":"Danika Danika","trips":250,"airline":[{"id":5,"name":"Eva Air","country":"Taiwan","logo":"https://upload.wikimedia.org/wikipedia/en/thumb/e/ed/EVA_Air_logo.svg/250px-EVA_Air_logo.svg.png","slogan":"Sharing the World, Flying Together","head_quaters":"376, Hsin-Nan Rd., Sec. 1, Luzhu, Taoyuan City, Taiwan","website":"www.evaair.com","established":"1989"}],"__v":0,"_id":"b86ba361-fb9a-44b6-961c-7ec78d18fea8"},"4348f4fe-87b4-4b54-b5d4-27ffa89142e0":{"name":"Danika Danika","trips":250,"airline":[{"id":5,"name":"Eva Air","country":"Taiwan","logo":"https://upload.wikimedia.org/wikipedia/en/thumb/e/ed/EVA_Air_logo.svg/250px-EVA_Air_logo.svg.png","slogan":"Sharing the World, Flying Together","head_quaters":"376, Hsin-Nan Rd., Sec. 1, Luzhu, Taoyuan City, Taiwan","website":"www.evaair.com","established":"1989"}],"__v":0,"_id":"4348f4fe-87b4-4b54-b5d4-27ffa89142e0"}}